{"title":"GATEAU AU CARAMBAR","slug":"gateau-au-carambar","meta":"Pour 10 personnespréparation 15mn cuisson 5mn Repos 12H00","parsedMeta":{"portions":"10","prep":"15mn","cook":"5mn"},"ingredients":["44 carambars","185g de beurre","200g de chamallows","¼ de paquet de rice krispies (env. 80g)"],"steps":["1. Mettez dans un grand saladier en Pyrex, en grès ou en porcelaine tous les carambars, les chamallows et le beurre.","2. Glissez le saladier au four à micro-ondes et laissez cuire 5mn à puissance maximale.","3. Lissez le tout, une fois la cuisson terminée, avec une spatule en silicone : la pâte doit former un ruban. Incorporez les Rice Krispies.","4. Etalez la pâte dans un moule en silicone rectangulaire et laissez refroidir. Laissez reposer 12 h au réfrigérateur avant de découper en morceaux et de croquer."],"images":[{"id":"rId12","path":"image2.jpeg"}]}