{"title":"TARTE AUX POMMES, BANANES & NOIX DE COCO","slug":"tarte-aux-pommes-bananes-and-noix-de-coco","meta":"Pour 6 personnespréparation 15mncuisson 35mn","parsedMeta":{"portions":"6","cook":"35mn"},"ingredients":["1 pâte brisée","1 jus de citron","3 bananes","2 œufs","3 pommes","15cl de crème liquide","100g de noix de coco","3 cl de rhum"],"steps":["1° Préchauffez le four TH 210°. Garnissez le moule de la pâte à tarte et piquez le fond avec une fourchette.","2° Ecrasez une banane à la fourchette dans un saladier, versez le rhum, le jus de citron, les œufs 1 à 1 tout en fouettent puis la crème liquide et la noix de coco.","3° Découpez en rondelles les 2 dernières bananes.","4° Pelez et épépinez les pommes et coupez-les en petits cubes. Parsemez –en le fond de tarte puis versez la préparation dessus. Enfournez.","5° Laissez tiédir 10mn avant de servir tiède ou froid."],"images":[{"id":"rId5","path":"image1.png"}]}