{"title":"FEUILLETTE AU CHEVRE DEMAXIME","slug":"feuillette-au-chevre-demaxime","meta":"Pour3 personnes ou 4 personnespréparation 10mn","parsedMeta":{"portions":"3","prep":"10mn"},"ingredients":["1 bûche de chèvre","1 œuf","1 pâte feuilletée","Des tomates séchées"],"steps":["1° Préchauffez le four TH 200/210°C.","2° Coupez la bûche de chèvre en rondelles d’1/2cl d’épaisseur.","3° Etalez la pâte et coupez avec l’emporte pièce des disques. Pour 9 feuilletées il faut 18 disques.","4° Posez les disques sur le papier de cuisson de la pâte ensuite une rondelle de chèvre et un autre disque pour fermer. Variante avec un morceau de tomate séchée.","5° Badigeonnez le dessus des disques avec un jaune d’œuf pour qu’ils dorent.","6° Au four pendant 20mn. Servez avec une salade."]}